finance_calculator/__init__.py
finance_calculator/__main__.py
finance_calculator/api.py
finance_calculator/cli.py
finance_calculator/calculators/__init__.py
finance_calculator/calculators/portfolio_calculator.py
finance_calculator/calculators/ratio_calculator.py
finance_calculator-0.0.6.dist-info/AUTHORS.rst
finance_calculator-0.0.6.dist-info/LICENSE
finance_calculator-0.0.6.dist-info/METADATA
finance_calculator-0.0.6.dist-info/WHEEL
finance_calculator-0.0.6.dist-info/entry_points.txt
finance_calculator-0.0.6.dist-info/top_level.txt
finance_calculator-0.0.6.dist-info/RECORD
