Metadata-Version: 2.1
Name: finance-calculator
Version: 0.0.6
Summary: A simple python tool for calculating ratios used to measure portfolio performance.
Home-page: https://github.com/sprksh/finance-calculator
Author: Surya Prakash
Author-email: sprksh.j@gmail.com
License: BSD-2-Clause
Project-URL: Documentation, https://finance-calculator.readthedocs.io/
Project-URL: Changelog, https://finance-calculator.readthedocs.io/en/latest/changelog.html
Project-URL: Issue Tracker, https://github.com/sprksh/finance-calculator/issues
Platform: UNKNOWN
Classifier: Development Status :: 5 - Production/Stable
Classifier: Intended Audience :: Developers
Classifier: License :: OSI Approved :: BSD License
Classifier: Operating System :: Unix
Classifier: Operating System :: POSIX
Classifier: Operating System :: Microsoft :: Windows
Classifier: Programming Language :: Python
Classifier: Programming Language :: Python :: 2.7
Classifier: Programming Language :: Python :: 3
Classifier: Programming Language :: Python :: 3.5
Classifier: Programming Language :: Python :: 3.6
Classifier: Programming Language :: Python :: 3.7
Classifier: Programming Language :: Python :: 3.8
Classifier: Programming Language :: Python :: Implementation :: CPython
Classifier: Programming Language :: Python :: Implementation :: PyPy
Classifier: Topic :: Utilities
Requires-Python: >=2.7, !=3.0.*, !=3.1.*, !=3.2.*, !=3.3.*, !=3.4.*
Requires-Dist: numpy (>=1.18.0)
Requires-Dist: pandas (>=0.25.0)
